optnet/__init__.py
optnet-0.0.1.dist-info/LICENSE
optnet-0.0.1.dist-info/METADATA
optnet-0.0.1.dist-info/WHEEL
optnet-0.0.1.dist-info/top_level.txt
optnet-0.0.1.dist-info/RECORD
