Metadata-Version: 2.1
Name: optnet
Version: 0.0.1
Summary: optnet
Home-page: https://github.com/zhangdongkun98/optnet
Author: Zhang Dongkun
Author-email: zhangdongkun98@gmail.com
License: UNKNOWN
Platform: UNKNOWN
